kittylog/__init__.py
kittylog/__version__.py
kittylog/ai.py
kittylog/ai_utils.py
kittylog/auth_cli.py
kittylog/cache.py
kittylog/cli.py
kittylog/commit_analyzer.py
kittylog/errors.py
kittylog/init_cli.py
kittylog/language_cli.py
kittylog/main.py
kittylog/model_cli.py
kittylog/output.py
kittylog/postprocess.py
kittylog/release_cli.py
kittylog/tag_operations.py
kittylog/workflow.py
kittylog/workflow_ui.py
kittylog/workflow_validation.py
kittylog/changelog/__init__.py
kittylog/changelog/boundaries.py
kittylog/changelog/content.py
kittylog/changelog/insertion.py
kittylog/changelog/io.py
kittylog/changelog/updater.py
kittylog/config/__init__.py
kittylog/config/cli.py
kittylog/config/data.py
kittylog/config/loader.py
kittylog/config/options.py
kittylog/config/secure.py
kittylog/constants/__init__.py
kittylog/constants/audiences.py
kittylog/constants/changelog_sections.py
kittylog/constants/commit_keywords.py
kittylog/constants/enums.py
kittylog/constants/env_defaults.py
kittylog/constants/languages.py
kittylog/constants/limits.py
kittylog/constants/logging.py
kittylog/constants/utility.py
kittylog/mode_handlers/__init__.py
kittylog/mode_handlers/boundary.py
kittylog/mode_handlers/missing.py
kittylog/mode_handlers/unreleased.py
kittylog/oauth/__init__.py
kittylog/oauth/claude_code.py
kittylog/oauth/qwen_oauth.py
kittylog/oauth/token_store.py
kittylog/prompt/__init__.py
kittylog/prompt/detail_limits.py
kittylog/prompt/json_schema.py
kittylog/prompt/system.py
kittylog/prompt/system_developers.py
kittylog/prompt/system_stakeholders.py
kittylog/prompt/system_users.py
kittylog/prompt/user.py
kittylog/providers/README.md
kittylog/providers/__init__.py
kittylog/providers/anthropic.py
kittylog/providers/azure_openai.py
kittylog/providers/base.py
kittylog/providers/cerebras.py
kittylog/providers/chutes.py
kittylog/providers/claude_code.py
kittylog/providers/custom_anthropic.py
kittylog/providers/custom_openai.py
kittylog/providers/deepseek.py
kittylog/providers/error_handler.py
kittylog-3.1.0.dist-info/METADATA
kittylog-3.1.0.dist-info/WHEEL
kittylog-3.1.0.dist-info/entry_points.txt
kittylog-3.1.0.dist-info/licenses/LICENSE
kittylog-3.1.0.dist-info/RECORD
