Metadata-Version: 2.4
Name: kittylog
Version: 3.1.0
Summary: AI-powered changelog updater that uses git tags to update CHANGELOG.md files
Project-URL: Homepage, https://github.com/cellwebb/kittylog
Project-URL: Documentation, https://github.com/cellwebb/kittylog#readme
Project-URL: Repository, https://github.com/cellwebb/kittylog.git
Project-URL: Issues, https://github.com/cellwebb/kittylog/issues
Project-URL: Changelog, https://github.com/cellwebb/kittylog/blob/main/CHANGELOG.md
Project-URL: Source, https://github.com/cellwebb/kittylog
Author-email: cellwebb <cellwebb@users.noreply.github.com>
License-Expression: MIT
License-File: LICENSE
Keywords: automation,changelog,git,github,pull-request,tags,versioning
Classifier: Development Status :: 4 - Beta
Classifier: Programming Language :: Python
Classifier: Programming Language :: Python :: 3.10
Classifier: Programming Language :: Python :: 3.11
Classifier: Programming Language :: Python :: 3.12
Classifier: Programming Language :: Python :: 3.13
Classifier: Programming Language :: Python :: 3.14
Classifier: Programming Language :: Python :: Implementation :: CPython
Classifier: Programming Language :: Python :: Implementation :: PyPy
Requires-Python: >=3.10
Requires-Dist: click>=8.3.1
Requires-Dist: gitpython>=3.1.45
Requires-Dist: halo>=0.0.31
Requires-Dist: httpx>=0.28.1
Requires-Dist: packaging>=25.0
Requires-Dist: python-dotenv>=1.2.1
Requires-Dist: questionary>=2.1.1
Requires-Dist: rich>=14.2.0
Requires-Dist: tiktoken>=0.12.0
Provides-Extra: dev
Requires-Dist: build>=1.3.0; extra == 'dev'
Requires-Dist: codecov>=2.1.13; extra == 'dev'
Requires-Dist: pytest-asyncio>=1.3.0; extra == 'dev'
Requires-Dist: pytest-cov>=7.0.0; extra == 'dev'
Requires-Dist: pytest>=9.0.1; extra == 'dev'
Requires-Dist: ruff>=0.14.7; extra == 'dev'
Requires-Dist: twine>=6.2.0; extra == 'dev'
